playsound-stubs/METADATA.toml
playsound-stubs/__init__.pyi
playsound-stubs/py.typed
types_playsound-1.3.1.20241019.dist-info/METADATA
types_playsound-1.3.1.20241019.dist-info/WHEEL
types_playsound-1.3.1.20241019.dist-info/top_level.txt
types_playsound-1.3.1.20241019.dist-info/RECORD
